fmstream/__init__.py
fmstream/api.py
fmstream/exceptions.py
fmstream/models.py
fmstream/scraper.py
fmstream-1.0.1.dist-info/licenses/LICENSE
fmstream-1.0.1.dist-info/METADATA
fmstream-1.0.1.dist-info/WHEEL
fmstream-1.0.1.dist-info/top_level.txt
fmstream-1.0.1.dist-info/RECORD
