Metadata-Version: 2.4
Name: fmstream
Version: 1.0.1
Summary: A Python library for scraping FM radio station data from fmstream.org
Home-page: https://github.com/fmstream-py/fmstream
Author: HaoWasabi
Author-email: truonggiahao24@example.com
Classifier: Development Status :: 4 - Beta
Classifier: Intended Audience :: Developers
Classifier: License :: OSI Approved :: MIT License
Classifier: Operating System :: OS Independent
Classifier: Programming Language :: Python :: 3
Classifier: Programming Language :: Python :: 3.7
Classifier: Programming Language :: Python :: 3.8
Classifier: Programming Language :: Python :: 3.9
Classifier: Programming Language :: Python :: 3.10
Classifier: Programming Language :: Python :: 3.11
Requires-Python: >=3.7
License-File: LICENSE
Requires-Dist: requests>=2.25.0
Requires-Dist: beautifulsoup4>=4.9.0
Requires-Dist: fastapi>=0.68.0
Requires-Dist: pydantic>=1.8.0
Requires-Dist: uvicorn>=0.15.0
Provides-Extra: dev
Requires-Dist: pytest>=6.0; extra == "dev"
Requires-Dist: pytest-cov>=2.0; extra == "dev"
Requires-Dist: black>=21.0; extra == "dev"
Requires-Dist: flake8>=3.8; extra == "dev"
Provides-Extra: api
Requires-Dist: fastapi>=0.68.0; extra == "api"
Requires-Dist: pydantic>=1.8.0; extra == "api"
Requires-Dist: uvicorn>=0.15.0; extra == "api"
Dynamic: author
Dynamic: author-email
Dynamic: classifier
Dynamic: description
Dynamic: description-content-type
Dynamic: home-page
Dynamic: license-file
Dynamic: provides-extra
Dynamic: requires-dist
Dynamic: requires-python
Dynamic: summary
